autoprotocol/__init__.py
autoprotocol/builders.py
autoprotocol/compound.py
autoprotocol/constants.py
autoprotocol/container.py
autoprotocol/container_type.py
autoprotocol/harness.py
autoprotocol/informatics.py
autoprotocol/instruction.py
autoprotocol/protocol.py
autoprotocol/unit.py
autoprotocol/util.py
autoprotocol/version.py
autoprotocol/liquid_handle/__init__.py
autoprotocol/liquid_handle/dispense.py
autoprotocol/liquid_handle/liquid_class.py
autoprotocol/liquid_handle/liquid_handle_method.py
autoprotocol/liquid_handle/mix.py
autoprotocol/liquid_handle/tip_type.py
autoprotocol/liquid_handle/transfer.py
autoprotocol/types/__init__.py
autoprotocol/types/builders.py
autoprotocol/types/protocol.py
autoprotocol/types/ref.py
autoprotocol-10.3.0.dist-info/AUTHORS.rst
autoprotocol-10.3.0.dist-info/LICENSE.rst
autoprotocol-10.3.0.dist-info/METADATA
autoprotocol-10.3.0.dist-info/WHEEL
autoprotocol-10.3.0.dist-info/top_level.txt
autoprotocol-10.3.0.dist-info/RECORD
