Metadata-Version: 2.1
Name: autoprotocol
Version: 10.3.0
Summary: Python library for generating Autoprotocol
Home-page: https://github.com/autoprotocol/autoprotocol-python
Maintainer: The Autoprotocol Development Team
Maintainer-email: support@strateos.com
License: BSD
Classifier: Development Status :: 5 - Production/Stable
Classifier: Intended Audience :: Developers
Classifier: Intended Audience :: Science/Research
Classifier: Operating System :: MacOS :: MacOS X
Classifier: Operating System :: Microsoft :: Windows
Classifier: Operating System :: Unix
Classifier: Programming Language :: Python
Classifier: Topic :: Scientific/Engineering
Classifier: Topic :: Software Development
Classifier: Programming Language :: Python :: 3.7
Classifier: Programming Language :: Python :: 3.8
Classifier: Programming Language :: Python :: 3.9
Classifier: Programming Language :: Python :: 3.10
Requires-Python: >=3.7
License-File: LICENSE.rst
License-File: AUTHORS.rst
Requires-Dist: Pint (==0.9)
Provides-Extra: docs
Requires-Dist: jinja2 (==3.0.0) ; extra == 'docs'
Requires-Dist: releases (<2,>=1.6.3) ; extra == 'docs'
Requires-Dist: sphinx (==4.2.0) ; extra == 'docs'
Requires-Dist: sphinx-rtd-theme (==1.0.0) ; extra == 'docs'
Requires-Dist: readthedocs-sphinx-search (==0.1.1) ; extra == 'docs'
Requires-Dist: semantic-version (==2.6.0) ; extra == 'docs'
Requires-Dist: six (<2,>=1.15.0) ; extra == 'docs'
Requires-Dist: click (==8.0.2) ; extra == 'docs'
Requires-Dist: black (==22.3.0) ; extra == 'docs'
Provides-Extra: test
Requires-Dist: coverage (<7,>=6) ; extra == 'test'
Requires-Dist: pre-commit (<3,>=2.4) ; extra == 'test'
Requires-Dist: pylint (==2.5.2) ; extra == 'test'
Requires-Dist: pytest (<7,>=6.2.5) ; extra == 'test'
Requires-Dist: pytest-cov (<4,>=3.0.0) ; extra == 'test'
Requires-Dist: tox (<4,>=3.15) ; extra == 'test'
